<?xml version="1.0" encoding="utf-8"?>
<cinimaticCaption>
	<caption startFrame="10" endFrame="140" color="4294967295">CUTTER: Hlášení kapitána, 4. února 2531.</caption>
	<caption startFrame="145" endFrame="270" color="4294967295">Pět let. Pět dlouhých let.</caption>
	<caption startFrame="280" endFrame="400" color="4294967295">Tak dlouho nám trvalo dostat Harvest zpět.</caption>
	<caption startFrame="1110" endFrame="1180" color="4294967295">Zpočátku šlo všechno dobře,...</caption>
	<caption startFrame="1190" endFrame="1310" color="4294967295">pak najednou porážka za porážkou...</caption>
	<caption startFrame="1440" endFrame="1560" color="4294967295">a ztráta za ztrátou...</caption>
	<caption startFrame="1620" endFrame="1740" color="4294967295">a plánované rychlé a rozhodné vítězství...</caption>
	<caption startFrame="1790" endFrame="1910" color="4294967295">se změnilo v pět let trvající peklo.</caption>
	<caption startFrame="2040" endFrame="2160" color="4294967295">A to je dnešní Harvest,...</caption>
	<caption startFrame="2170" endFrame="2240" color="4294967295">změnil se v samotné peklo.</caption>
	<caption startFrame="2250" endFrame="2360" color="4294967295">Ale teď je znovu náš.</caption>
	<caption startFrame="2670" endFrame="2940" color="4294967295" SubtitleForVisualElement="true">SYSTÉM EPSILON INDI, HARVEST, 4. ÚNORA 2531</caption>
	<caption startFrame="2980" endFrame="3060" color="4294967295" SubtitleForVisualElement="true">20 LET PŘED UDÁLOSTÍ S HALO</caption>
	<caption startFrame="3780" endFrame="3830" color="4294967295">CUTTER: Serino. Hlášení?</caption>
	<caption startFrame="3840" endFrame="3920" color="4294967295">SERINA: Dosáhli jsme standardní orbity. Všechny systémy v normálu.</caption>
	<caption startFrame="3930" endFrame="4010" color="4294967295">CUTTER: Připravte se na výsadek, aktivujte zbraňové systémy.</caption>
	<caption startFrame="4020" endFrame="4070" color="4294967295">SERINA: Očekáváte nějaké problémy, kapitáne?</caption>
	<caption startFrame="4080" endFrame="4140" color="4294967295">CUTTER: Harvest je zpátky v našich rukou,</caption>
	<caption startFrame="4140" endFrame="4260" color="4294967295">ale Covenant se s tím určitě jen tak nesmířil.</caption>
	<caption startFrame="4320" endFrame="4370" color="4294967295">Seržante Forgi. Hlášení.</caption>
	<caption startFrame="4380" endFrame="4430" color="4294967295">FORGE: Je tu spousta nepřátel, kapitáne,</caption>
	<caption startFrame="4440" endFrame="4490" color="4294967295">a našli něco ukryté v ledu.</caption>
	<caption startFrame="4500" endFrame="4615" color="4294967295">CUTTER: Zatraceně! To komplikuje naši misi. Andersová, co jste zjistila?</caption>
	<caption startFrame="4620" endFrame="4690" color="4294967295">ANDERSOVÁ: Kapitáne, monitoring severní polární oblasti</caption>
	<caption startFrame="4700" endFrame="4770" color="4294967295">odhalil zajímavou aktivitu Covenantu na povrchu.</caption>
	<caption startFrame="4780" endFrame="4840" color="4294967295">Jsou tam nějaké konstrukce.</caption>
	<caption startFrame="4860" endFrame="4920" color="4294967295">SERINA: Co myslíte, že tam hledají?</caption>
	<caption startFrame="4950" endFrame="5000" color="4294967295">CUTTER: To musíme zjistit.</caption>
	<caption startFrame="5010" endFrame="5075" color="4294967295">Převedeme základnu Alpha Base do operačního stavu</caption>
	<caption startFrame="5080" endFrame="5120" color="4294967295">a dostaneme tu oblast pod kontrolu.</caption>
	<caption startFrame="5130" endFrame="5180" color="4294967295">ANDERSOVÁ: Půjdu si připravit svoji výbavu, kapitáne.</caption>
	<caption startFrame="5190" endFrame="5290" color="4294967295">FORGE: Milá dámo, v žádném případě nepůjdete dolů s prvním výsadkem.</caption>
	<caption startFrame="5400" endFrame="5460" color="4294967295">CUTTER: Seržante Forgi, stáhněte se na základnu Alpha Base.</caption>
	<caption startFrame="5460" endFrame="5505" color="4294967295">Posílám vám nějaké zálohy.</caption>
	<caption startFrame="5510" endFrame="5560" color="4294967295">FORGE: OK. Forge končí.</caption>
	<caption startFrame="5570" endFrame="5650" color="4294967295">SERINA: Takže... nic moc těžkého?</caption>
	<caption startFrame="5730" endFrame="5810" color="4294967295">CUTTER: Může to být klíč k celé této válce, Serino.</caption>
	<caption startFrame="5815" endFrame="5860" color="4294967295">Stojí to za to riziko.</caption>
</cinimaticCaption>