<?xml version="1.0" encoding="utf-8"?>
<cinimaticCaption>
	<caption startFrame="120" endFrame="190" color="4294967295">Каттер: Что, она просто целилась сюда?</caption>
	<caption startFrame="200" endFrame="275" color="4294967295">Андерс: За полминуты я должна была ее исследовать?</caption>
	<caption startFrame="280" endFrame="375" color="4294967295">Да, она просто целилась во вторую систему.</caption>
	<caption startFrame="380" endFrame="455" color="4294967295">Серина: А именно в колонию Аркадия.</caption>
	<caption startFrame="460" endFrame="555" color="4294967295">Население около трех миллионов. Исследовано мало,</caption>
	<caption startFrame="560" endFrame="650" color="4294967295">но зато отличные курорты.</caption>
	<caption startFrame="660" endFrame="735" color="4294967295">Андерс: Там что-то есть, капитан, и нам нужно</caption>
	<caption startFrame="740" endFrame="790" color="4294967295">добраться до этого быстрее Ковенанта.</caption>
	<caption startFrame="800" endFrame="860" color="4294967295">Каттер: Нам поручено обследовать Жатву.</caption>
	<caption startFrame="870" endFrame="970" color="4294967295">Мы почти ничего не знаем о том, что там происходит.</caption>
	<caption startFrame="970" endFrame="1045" color="4294967295">Андерс: Понимаю, капитан. Но я все больше убеждаюсь,</caption>
	<caption startFrame="1050" endFrame="1150" color="4294967295">что для этого нужно лететь на Аркадию.</caption>
	<caption startFrame="1200" endFrame="1275" color="4294967295">Каттер: Хорошо, профессор. Я все улажу с адмиралом Коулом.</caption>
	<caption startFrame="1280" endFrame="1350" color="4294967295">Серина, держи курс на Аркадию.</caption>
	<caption startFrame="1360" endFrame="1475" color="4294967295">Серина: Есть начать идиотский перелет на Аркадию.</caption>
	<caption startFrame="1480" endFrame="1560" color="4294967295">Запускаю сверхсветовые.</caption>
	<caption startFrame="1570" endFrame="1640" color="4294967295">Андерс: Серина, убирайся вон.</caption>
	<caption startFrame="1820" endFrame="1920" color="4294967295" SubtitleForVisualElement="true">СИСТЕМА ПРОЦИОНА — АРКАДИЯ, 9 ФЕВРАЛЯ 2531 ГОДА</caption>
	<caption startFrame="1940" endFrame="1990" color="4294967295">Каттер: Серина, доложи обстановку.</caption>
	<caption startFrame="2000" endFrame="2105" color="4294967295">Серина: Два корабля Ковенанта вышли из подпространства у Аркадии.</caption>
	<caption startFrame="2110" endFrame="2235" color="4294967295">«Белфаст», «Столп Осени», «Техас» и «Армстронг» открыли огонь</caption>
	<caption startFrame="2240" endFrame="2325" color="4294967295">и застали врасплох один из кораблей.</caption>
	<caption startFrame="2330" endFrame="2425" color="4294967295">«Техас» и «Белфаст» погибли, на «Армстронге» утечка воздуха,</caption>
	<caption startFrame="2430" endFrame="2495" color="4294967295">а «Столп» сильно поврежден.</caption>
	<caption startFrame="2500" endFrame="2560" color="4294967295">Второй корабль что-то делает на планете.</caption>
	<caption startFrame="2570" endFrame="2620" color="4294967295">Каттер: Что именно он там делает?</caption>
	<caption startFrame="2630" endFrame="2780" color="4294967295">Серина: Не знаю. Стоп, я поймала сигнал. Только звук.</caption>
	<caption startFrame="2790" endFrame="2875" color="4294967295">Радиограмма: Нам некуда отступать! Армии врага проникли в город</caption>
	<caption startFrame="2880" endFrame="2985" color="4294967295">и приближаются к космопорту. Мы эвакуируем жителей.</caption>
	<caption startFrame="2990" endFrame="3040" color="4294967295">Помогите!</caption>
	<caption startFrame="3050" endFrame="3110" color="4294967295">Серина: Есть изображение, капитан.</caption>
	<caption startFrame="3680" endFrame="3760" color="4294967295">Каттер: Серина. Запускай капсулы. Общая тревога.</caption>
</cinimaticCaption>