<?xml version="1.0" encoding="utf-8"?>
<cinimaticCaption>
	<caption startFrame="41" endFrame="135" color="4294967295">では このエリアがシールドで覆われているのか？</caption>
	<caption startFrame="149" endFrame="180" color="4294967295">はい 艦長</caption>
	<caption startFrame="183" endFrame="270" color="4294967295">内部は見えませんが 明らかにコヴナントの仕業です</caption>
	<caption startFrame="275" endFrame="358" color="4294967295">なるほど 正体を突き止めねば</caption>
	<caption startFrame="363" endFrame="440" color="4294967295">キャノン砲でシールドを破壊できないか？</caption>
	<caption startFrame="453" endFrame="505" color="4294967295">内部まで破壊しかねません</caption>
	<caption startFrame="515" endFrame="630" color="4294967295">コヴナントのシールドは超高温のプラズマに弱いはずです</caption>
	<caption startFrame="651" endFrame="712" color="4294967295">プラズマ砲を積んだライノは？</caption>
	<caption startFrame="729" endFrame="825" color="4294967295">オータムがプロトタイプを数台所持しています</caption>
	<caption startFrame="846" endFrame="910" color="4294967295">パワーセッティングに時間がかかります</caption>
	<caption startFrame="918" endFrame="960" color="4294967295">地上に降りなくては</caption>
	<caption startFrame="981" endFrame="1070" color="4294967295">教授 軍曹 シールドを破壊するぞ</caption>
	<caption startFrame="1080" endFrame="1150" color="4294967295">ああ… また子守りですか</caption>
</cinimaticCaption>